jwodder_ps1/__init__.py
jwodder_ps1/__main__.py
jwodder_ps1/git.py
jwodder_ps1/info.py
jwodder_ps1/py.typed
jwodder_ps1/styles.py
jwodder_ps1-0.7.2.dist-info/METADATA
jwodder_ps1-0.7.2.dist-info/WHEEL
jwodder_ps1-0.7.2.dist-info/entry_points.txt
jwodder_ps1-0.7.2.dist-info/licenses/LICENSE
jwodder_ps1-0.7.2.dist-info/RECORD
