Metadata-Version: 2.3
Name: jwodder-ps1
Version: 0.7.2
Summary: Yet another bash/zsh custom prompt script
Project-URL: Source Code, https://github.com/jwodder/ps1.py
Project-URL: Bug Tracker, https://github.com/jwodder/ps1.py/issues
Author-email: John Thorvald Wodder II <ps1@varonathe.org>
License-Expression: MIT
License-File: LICENSE
Keywords: bash,git,prompt,ps1,zsh
Classifier: Environment :: Console
Classifier: Intended Audience :: Developers
Classifier: Intended Audience :: End Users/Desktop
Classifier: Intended Audience :: Information Technology
Classifier: License :: OSI Approved :: MIT License
Classifier: Operating System :: POSIX
Classifier: Programming Language :: Python :: 3
Classifier: Programming Language :: Python :: 3 :: Only
Classifier: Programming Language :: Python :: 3.9
Classifier: Programming Language :: Python :: 3.10
Classifier: Programming Language :: Python :: 3.11
Classifier: Programming Language :: Python :: 3.12
Classifier: Programming Language :: Python :: Implementation :: CPython
Classifier: Programming Language :: Python :: Implementation :: PyPy
Classifier: Topic :: Software Development :: Version Control :: Git
Classifier: Topic :: System :: Shells
Classifier: Typing :: Typed
Requires-Python: >=3.9
